seldetpacceshi/__init__.py
seldetpacceshi/main.cpython-311-darwin.so
seldetpacceshi/timer.cpython-311-darwin.so
seldetpacceshi-0.1.0.dist-info/LICENCE.txt
seldetpacceshi-0.1.0.dist-info/METADATA
seldetpacceshi-0.1.0.dist-info/WHEEL
seldetpacceshi-0.1.0.dist-info/entry_points.txt
seldetpacceshi-0.1.0.dist-info/top_level.txt
seldetpacceshi-0.1.0.dist-info/RECORD
